casedi/__init__.py
casedi/enrichment.py
casedi/expression.py
casedi/survival.py
casedi/util.py
casedi-0.0.3.dist-info/METADATA
casedi-0.0.3.dist-info/WHEEL
casedi-0.0.3.dist-info/licenses/LICENSE
casedi-0.0.3.dist-info/RECORD
