Metadata-Version: 2.3
Name: casedi
Version: 0.0.3
Summary: Cancer ASE driver identification (CASEDI)
Project-URL: Homepage, https://github.com/maggietsui/CASEDI
Project-URL: Issues, https://github.com/maggietsui/CASEDI/issues
Author-email: Maggie Tsui <margaret.tsui@ucsf.edu>
License-File: LICENSE
Classifier: License :: OSI Approved :: MIT License
Classifier: Operating System :: OS Independent
Classifier: Programming Language :: Python :: 3
Requires-Python: >=3.9.5
Requires-Dist: matplotlib>=3.4.2
Requires-Dist: numpy>=1.23.3
Requires-Dist: pandas>=1.3.1
Requires-Dist: scikit-survival
Requires-Dist: scipy>=1.9.1
Requires-Dist: statsmodels>=0.13.2
